jock/__init__.py
jock/__main__.py
jock/cli.py
jock/config.py
jock/git.py
jock/utils.py
tests/__init__.py
tests/utils.py
tests/unit/__init__.py
tests/unit/test_cli.py
tests/unit/test_config.py
tests/unit/test_git.py
tests/unit/test_utils.py
git_jock-0.2.1.dist-info/LICENSE.txt
git_jock-0.2.1.dist-info/METADATA
git_jock-0.2.1.dist-info/WHEEL
git_jock-0.2.1.dist-info/top_level.txt
git_jock-0.2.1.dist-info/RECORD
