Metadata-Version: 2.1
Name: git-jock
Version: 0.2.1
Summary: Git helper for multi-repository management
Home-page: UNKNOWN
Author: Gavin Fenton
Author-email: contact@gavinfenton.com
License: UNKNOWN
Platform: UNKNOWN
Classifier: Programming Language :: Python :: 3
Classifier: License :: OSI Approved :: MIT License
Classifier: Operating System :: POSIX :: Linux
Classifier: Intended Audience :: Developers
Classifier: Intended Audience :: Information Technology
Classifier: Intended Audience :: System Administrators
Classifier: Natural Language :: English
Classifier: Topic :: Software Development :: Build Tools
Classifier: Topic :: Software Development :: Version Control
Classifier: Topic :: Software Development :: Version Control :: Git
Requires-Python: >=3.7
